{
  "GALLETITAS CON GLUTEN (NOMBRE COMERCIAL)": "Nuez de la India MEKÉ",
  "MARCA": "Nuez",
  "DENOMINACIÓN DE VENTA": "nuez de la india horneada con sal",
  "SABOR (DULCE: 0; SALADO: 1)": 1,
  "TIPO DE GALLETITAS (SIMPLE: 0; RELLENA: 1)": 0,
  "CANTIDAD (g)": "",
  "CANTIDAD PORCIÓN (g)": 100.0,
  "VALOR ENERGÉTICO (Kcal/ porción)": "",
  "VALOR ENERGÉTICO (Kcal/ 100 g)": "",
  "CARBOHIDRATOS (g/porción)": 27.0,
  "CARBOHIDRATOS (g/ 100 g)": 27.0,
  "AZÚCARES TOTALES  (g/ porción)": 0.0,
  "AZÚCARES TOTALES  (g/ 100 g)": 0.0,
  "AZÚCARES AÑADIDOS (g/ porción)": 0.0,
  "AZÚCARES AÑADIDOS (g/ 100 g)": 0.0,
  "PROTEÍNAS  (g/ porción)": 16.0,
  "PROTEÍNAS  (g/ 100 g)": 16.0,
  "GRASAS TOTALES (g/ porción)": "",
  "GRASAS TOTALES (g/ 100 g)": "",
  "GRASAS SATURADAS (g/ porción)": 7.3,
  "GRASAS SATURADAS (g/ 100 g)": 7.3,
  "GRASAS TRANS (g/ porción)": 0.0,
  "GRASAS TRANS (g/ 100 g)": 0.0,
  "GRASAS MONOINSATURADAS (g/ porción)": "",
  "GRASAS MONOINSATURADAS (g/ 100 g)": "",
  "GRASAS POLINSATURADAS (g/ porción)": "",
  "GRASAS POLINSATURADAS (g/ 100 g)": "",
  "COLESTEROL (g/ porción)": "",
  "COLESTEROL (g/ 100 g)": "",
  "FIBRA ALIMENTARIA  (g/ porción)": 7.6,
  "FIBRA ALIMENTARIA  (g/ 100 g)": 7.6,
  "SODIO  (mg/ porción)": 390.0,
  "SODIO  (mg/ 100 g)": 390.0,
  "EXCESO DE AZÚCARES": 0,
  "EXCESO EN GRASAS TOTALES ": 0,
  "EXCESO EN GRASAS SATURADAS": 1,
  "EXCESO EN SODIO": 1,
  "EXCESO EN CALORÍAS": 0,
  "CONTIENE EDULCORANTE": 0,
  "CONTIENE CAFEÍNA": 0,
  "OBSERVACIONES: VITAMINAS, MINERALES, OMEGA 3, OMEGA 9, FORTIFICACIÓN, ETC": "",
  "¿SE EXCLUYÓ? (SI/ NO)": "NO",
  "¿PORQUÉ? (ROTULO INCOMPLETO, GALLE DE ARROZ, ETC)": "",
  "Ingredientes": "",
  "Actualizado": "",
  "Fuente": ""
}